{
  "rules": {
    "//": "Locked to the owner account only. Reads/writes require this exact UID.",
    "//_owner": "Voltiq owner: oluwatimilehinakinsanmi@gmail.com",

    ".read": "auth != null && auth.uid === 'y5vPMGCZgvdouJxQRJrWVNNHXa82'",
    ".write": "auth != null && auth.uid === 'y5vPMGCZgvdouJxQRJrWVNNHXa82'",

    "readings": {
      ".indexOn": ["timestamp"],
      "$reading": {
        ".validate": "newData.hasChildren(['timestamp'])",
        "device_id": { ".validate": "newData.isString()" },
        "voltage":   { ".validate": "newData.isNumber()" },
        "current":   { ".validate": "newData.isNumber()" },
        "power":     { ".validate": "newData.isNumber()" },
        "energy":    { ".validate": "newData.isNumber()" },
        "frequency": { ".validate": "newData.isNumber()" },
        "cost":      { ".validate": "newData.isNumber()" },
        "timestamp": { ".validate": "newData.isString()" },
        "$other":    { ".validate": false }
      }
    },

    "devices": {
      "$device": {
        "name":         { ".validate": "newData.isString()" },
        "status":       { ".validate": "newData.isString()" },
        "location":     { ".validate": "newData.isString()" },
        "last_updated": { ".validate": "newData.isString()" },
        "$other":       { ".validate": false }
      }
    },

    "alerts": {
      ".indexOn": ["timestamp"],
      "$alert": {
        ".validate": "newData.hasChildren(['type', 'timestamp'])",
        "type":      { ".validate": "newData.isString()" },
        "message":   { ".validate": "newData.isString()" },
        "value":     { ".validate": "newData.isNumber()" },
        "timestamp": { ".validate": "newData.isString()" },
        "$other":    { ".validate": false }
      }
    }
  }
}
